asy_fifo/src/asy_fifo.v
////////////////////////////////////////////////////////////////////////////////
// 公司: NUDT
// 工程师: hjz
// 创建日期: 2022/11/14
// 设计名称: 异步fifo
// 模块名: asy_fifo
// 目标器件: 未定
// 工具软件版本号: vivado
// 描述:
// 同步fifo主模块
// 修订版本:
// rev1.0
// 额外注释:
// 待定
////////////////////////////////////////////////////////////////////////////////
module asy_fifo #(
    parameter             DEPTH = 64  ,
    parameter             WIDTH = 32
) (
  //----------写控制端---------------
    input                 wr_clk      ,
    input                 wr_rst_n    ,
    input                 wr_en       ,
    output                fifo_full   ,
    input [WIDTH-1:0]     wr_data     ,

    //----------读控制段---------------
    input                 rd_clk      ,
    input                 rd_rst_n    ,
    input                 rd_en       ,
    output                fifo_empty  ,
    output [WIDTH-1:0]    rd_data     
);

localparam ADDR_WIDTH = $clog2(DEPTH);

// 读写指针
reg [ADDR_WIDTH:0] wr_addr;
reg [ADDR_WIDTH:0] rd_addr;

// 延迟一拍和两拍的读写指针
reg [ADDR_WIDTH:0] wr_addr_g_r, wr_addr_g_rr;
reg [ADDR_WIDTH:0] rd_addr_g_r, rd_addr_g_rr;

// 读写地址的格雷码
wire [ADDR_WIDTH:0] wr_addr_g;
wire [ADDR_WIDTH:0] rd_addr_g;

// 双端口存储器的写使能和读使能
wire wen;
wire ren;

// 双端口存储器
dual_port_ram U1 #(
    .DEPTH(DEPTH),
    .WIDTH(WIDTH)
) (
    .wr_clk(wr_clk),
    .rd_clk(rd_clk),
    .wr_data(wr_data),
    .wen(wen),
    .ren(ren),

);

// 二进制码右移 1 位后与本身异或，其结果就是格雷码
assign wr_addr_g = wr_addr ^ (wr_addr >> 1);
assign rd_addr_g = rd_addr ^ (rd_addr >> 1);

// 判断空满逻辑
// 1. 格雷码高两位相反，其余位相同为满
// 2. 格雷码全部位相同为空
assign fifo_full = (wr_addr_g == {~rd_addr_g_rr[ADDR_WIDTH:ADDR_WIDTH-1], rd_addr_g_rr[ADDR_WIDTH-2:0]}) & wr_rst_n;
assign fifo_empty = (rd_addr_g == wr_addr_g_rr) & rd_rst_n;

always @(posedge wr_clk, negedge wr_rst_n) 
begin
    
end
endmodule

asy_fifo/src/asy_fifo_tb.v
////////////////////////////////////////////////////////////////////////////////
// 公司: NUDT
// 工程师: hjz
// 创建日期: 2022/11/14
// 设计名称: 异步fifo的testbench
// 模块名: asy_fifo_tb
// 目标器件: 未定
// 工具软件版本号: vivado
// 描述:
// 同步fifo主模块
// 修订版本:
// rev1.0
// 额外注释:
// 待定
////////////////////////////////////////////////////////////////////////////////
module asy_fifo_tb;

parameter   width = 8;
parameter   depth = 8;

reg wr_clk, wr_en, wr_rst_n;
reg rd_clk, rd_en, rd_rst_n;

reg [width - 1 : 0] wr_data;

wire fifo_full, fifo_empty;

wire [width - 1 : 0] rd_data;

//实例化
asy_fifo #(
    .DEPTH(depth),
    .WIDTH(width)
) myfifo(
    .wr_clk(wr_clk),
    .rd_clk(rd_clk),
    .wr_rst_n(wr_rst_n),
    .rd_rst_n(rd_rst_n),
    .wr_en(wr_en),
    .rd_en(rd_en),
    .wr_data(wr_data),
    .rd_data(rd_data),
    .fifo_empty(fifo_empty),
    .fifo_full(fifo_full)
);

//时钟
initial begin
    rd_clk = 0;
    forever #25 rd_clk = ~rd_clk;
end

initial begin
    wr_clk = 0;
    forever #30 wr_clk = ~wr_clk;
end

//波形显示
initial begin
    $dumpfile("asy_fifo_wave.vcd");        //生成的vcd文件名称
    $dumpvars(0, asy_fifo_tb);    //tb模块名称
end

//赋值
initial begin
    wr_en = 0;
    rd_en = 0;
    wr_rst_n = 1;
    rd_rst_n = 1;

    #10;
    wr_rst_n = 0;
    rd_rst_n = 0;

    #20;
    wr_rst_n = 1;
    rd_rst_n = 1;

    @(negedge wr_clk)
    wr_data = {$random} % 30;
    wr_en = 1;

    repeat(7) begin
        @(negedge wr_clk)
        wr_data = {$random} % 30;
    end

    @(negedge wr_clk)
    wr_en = 0;

    @(negedge rd_clk)
    rd_en = 1;

    repeat(7) begin
        @(negedge rd_clk);
    end

    @(negedge rd_clk)
    rd_en = 0;

    #150;

    @(negedge wr_clk)
    wr_en = 1;
    wr_data = {$random} % 30;

    repeat(15) begin
        @(negedge wr_clk)
        wr_data = {$random} % 30;
    end

    @(negedge wr_clk)
    wr_en = 0;

    #50;
    $finish;
end
endmodule

asy_fifo/sim/asy_fifo_wave.vcd
$date
	Mon Nov 14 16:42:30 2022
$end
$version
	Icarus Verilog
$end
$timescale
	1s
$end
$scope module asy_fifo_tb $end
$var wire 8 ! rd_data [7:0] $end
$var wire 1 " fifo_full $end
$var wire 1 # fifo_empty $end
$var reg 1 $ rd_clk $end
$var reg 1 % rd_en $end
$var reg 1 & rd_rst_n $end
$var reg 1 ' wr_clk $end
$var reg 8 ( wr_data [7:0] $end
$var reg 1 ) wr_en $end
$var reg 1 * wr_rst_n $end
$scope module myfifo $end
$var wire 1 # fifo_empty $end
$var wire 1 " fifo_full $end
$var wire 4 + rd_addr_g [3:0] $end
$var wire 1 $ rd_clk $end
$var wire 1 % rd_en $end
$var wire 1 & rd_rst_n $end
$var wire 1 , ren $end
$var wire 1 - wen $end
$var wire 4 . wr_addr_g [3:0] $end
$var wire 1 ' wr_clk $end
$var wire 8 / wr_data [7:0] $end
$var wire 1 ) wr_en $end
$var wire 1 * wr_rst_n $end
$var wire 8 0 rd_data [7:0] $end
$var reg 4 1 rd_addr [3:0] $end
$var reg 4 2 rd_addr_g_r [3:0] $end
$var reg 4 3 rd_addr_g_rr [3:0] $end
$var reg 4 4 wr_addr [3:0] $end
$var reg 4 5 wr_addr_g_r [3:0] $end
$var reg 4 6 wr_addr_g_rr [3:0] $end
$scope module U1 $end
$var wire 3 7 rd_addr [2:0] $end
$var wire 1 $ rd_clk $end
$var wire 1 , ren $end
$var wire 1 - wen $end
$var wire 3 8 wr_addr [2:0] $end
$var wire 1 ' wr_clk $end
$var wire 8 9 wr_data [7:0] $end
$var reg 8 : rd_data [7:0] $end
$upscope $end
$upscope $end
$upscope $end
$enddefinitions $end
#0
$dumpvars
bx :
bx 9
bx 8
bx 7
bx 6
bx 5
bx 4
bx 3
bx 2
bx 1
bx 0
bx /
bx .
0-
0,
bx +
1*
0)
bx (
0'
1&
0%
0$
x#
x"
bx !
$end
#10
b0 7
b0 +
b0 8
b0 .
b0 1
b0 5
b0 6
b0 4
b0 2
b0 3
0#
0"
0&
0*
#25
1$
#30
1#
1&
1*
1'
#50
0$
#60
1-
1)
b1000 (
b1000 /
b1000 9
0'
#75
1$
#90
b1 8
b1 .
b1 4
1'
#100
0$
#120
b11011 (
b11011 /
b11011 9
0'
#125
b1 5
1$
#150
b10 8
b11 .
b10 4
0$
1'
#175
0#
b11 5
b1 6
1$
#180
b111 (
b111 /
b111 9
0'
#200
0$
#210
b11 8
b10 .
b11 4
1'
#225
b11 6
b10 5
1$
#240
b10001 (
b10001 /
b10001 9
0'
#250
0$
#270
b100 8
b110 .
b100 4
1'
#275
b110 5
b10 6
1$
#300
b11011 (
b11011 /
b11011 9
0$
0'
#325
b110 6
1$
#330
b101 8
b111 .
b101 4
1'
#350
0$
#360
b10001 (
b10001 /
b10001 9
0'
#375
b111 5
1$
#390
b110 8
b101 .
b110 4
1'
#400
0$
#420
b101 (
b101 /
b101 9
0'
#425
b111 6
b101 5
1$
#450
b111 8
b100 .
b111 4
0$
1'
#475
b100 5
b101 6
1$
#480
b10110 (
b10110 /
b10110 9
0'
#500
0$
#510
0-
1"
b0 8
b1100 .
b1000 4
1'
#525
b100 6
b1100 5
1$
#540
0)
0'
#550
1,
1%
0$
#570
1'
#575
b1 7
b1 +
b1000 !
b1000 0
b1000 :
b1 1
b1100 6
1$
#600
0$
0'
#625
b10 7
b11 +
b11011 !
b11011 0
b11011 :
b10 1
1$
#630
b11 2
1'
#650
0$
#660
0'
#675
b11 7
b10 +
b111 !
b111 0
b111 :
b11 1
1$
#690
0"
b10 2
b11 3
1'
#700
0$
#720
0'
#725
b100 7
b110 +
b10001 !
b10001 0
b10001 :
b100 1
1$
#750
b10 3
b110 2
0$
1'
#775
b101 7
b111 +
b11011 !
b11011 0
b11011 :
b101 1
1$
#780
0'
#800
0$
#810
b111 2
b110 3
1'
#825
b110 7
b101 +
b10001 !
b10001 0
b10001 :
b110 1
1$
#840
0'
#850
0$
#870
b111 3
b101 2
1'
#875
b111 7
b100 +
b101 !
b101 0
b101 :
b111 1
1$
#900
0$
0'
#925
0,
1#
b0 7
b1100 +
b10110 !
b10110 0
b10110 :
b1000 1
1$
#930
b1100 2
b101 3
1'
#950
0%
0$
#960
0'
#975
1$
#990
b1100 3
1'
#1000
0$
#1020
0'
#1025
1$
#1050
0$
1'
#1075
1$
#1080
0'
#1100
0$
#1110
1'
#1125
1$
#1140
1-
b10101 (
b10101 /
b10101 9
1)
0'
#1150
0$
#1170
b1 8
b1101 .
b1001 4
1'
#1175
b1101 5
1$
#1200
b10011 (
b10011 /
b10011 9
0$
0'
#1225
0#
b1101 6
1$
#1230
b10 8
b1111 .
b1010 4
1'
#1250
0$
#1260
b10010 (
b10010 /
b10010 9
0'
#1275
b1111 5
1$
#1290
b11 8
b1110 .
b1011 4
1'
#1300
0$
#1320
b10001 (
b10001 /
b10001 9
0'
#1325
b1111 6
b1110 5
1$
#1350
b100 8
b1010 .
b1100 4
0$
1'
#1375
b1010 5
b1110 6
1$
#1380
b1001 (
b1001 /
b1001 9
0'
#1400
0$
#1410
b101 8
b1011 .
b1101 4
1'
#1425
b1010 6
b1011 5
1$
#1440
b10110 (
b10110 /
b10110 9
0'
#1450
0$
#1470
b110 8
b1001 .
b1110 4
1'
#1475
b1001 5
b1011 6
1$
#1500
b10011 (
b10011 /
b10011 9
0$
0'
#1525
b1001 6
1$
#1530
b111 8
b1000 .
b1111 4
1'
#1550
0$
#1560
b110 (
b110 /
b110 9
0'
#1575
b1000 5
1$
#1590
0-
1"
b0 8
b0 .
b0 4
1'
#1600
0$
#1620
b111 (
b111 /
b111 9
0'
#1625
b1000 6
b0 5
1$
#1650
0$
1'
#1675
b0 6
1$
#1680
b1100 (
b1100 /
b1100 9
0'
#1700
0$
#1710
1'
#1725
1$
#1740
b1111 (
b1111 /
b1111 9
0'
#1750
0$
#1770
1'
#1775
1$
#1800
0$
0'
#1825
1$
#1830
1'
#1850
0$
#1860
b1110 (
b1110 /
b1110 9
0'
#1875
1$
#1890
1'
#1900
0$
#1920
b1001 (
b1001 /
b1001 9
0'
#1925
1$
#1950
0$
1'
#1975
1$
#1980
b110 (
b110 /
b110 9
0'
#2000
0$
#2010
1'
#2025
1$
#2040
b0 (
b0 /
b0 9
0'
#2050
0$
#2070
1'
#2075
1$
#2100
0)
0$
0'
